foronoi/__init__.py
foronoi/algorithm.py
foronoi/contrib/__init__.py
foronoi/contrib/bounding_circle.py
foronoi/events/__init__.py
foronoi/events/circle_event.py
foronoi/events/event.py
foronoi/events/site_event.py
foronoi/graph/__init__.py
foronoi/graph/algebra.py
foronoi/graph/bounding_box.py
foronoi/graph/coordinate.py
foronoi/graph/half_edge.py
foronoi/graph/point.py
foronoi/graph/polygon.py
foronoi/graph/vertex.py
foronoi/nodes/__init__.py
foronoi/nodes/arc.py
foronoi/nodes/breakpoint.py
foronoi/nodes/internal_node.py
foronoi/nodes/leaf_node.py
foronoi/observers/__init__.py
foronoi/observers/debug_observer.py
foronoi/observers/message.py
foronoi/observers/observer.py
foronoi/observers/subject.py
foronoi/observers/tree_observer.py
foronoi/observers/voronoi_observer.py
foronoi/tests/__init__.py
foronoi/tests/unit.py
foronoi/tree/__init__.py
foronoi/tree/node.py
foronoi/tree/tree.py
foronoi/visualization/__init__.py
foronoi/visualization/tree_visualizer.py
foronoi/visualization/visualizer.py
foronoi-1.0.3.dist-info/LICENSE
foronoi-1.0.3.dist-info/METADATA
foronoi-1.0.3.dist-info/WHEEL
foronoi-1.0.3.dist-info/top_level.txt
foronoi-1.0.3.dist-info/RECORD
