Metadata-Version: 2.1
Name: foronoi
Version: 1.0.3
Summary: Fortune's algorithm for fast Voronoi diagram construction with extras.
Home-page: https://github.com/Yatoom/voronoi
Author: Jeroen van Hoof
Author-email: jeroen@jeroenvanhoof.nl
License: UNKNOWN
Keywords: voronoi,polygon,fortune,algorithm
Platform: UNKNOWN
Requires-Dist: numpy
Requires-Dist: matplotlib
Requires-Dist: graphviz
